tada/__init__.py
tada/perf_benchmark.py
tada/tada_a_bigoh.py
tada/util/__init__.py
tada/util/analysis.py
tada/util/arguments.py
tada/util/configuration.py
tada/util/constants.py
tada/util/display.py
tada/util/generate.py
tada/util/package.py
tada/util/read.py
tada/util/results.py
tada/util/run.py
tada/util/save.py
tada_predict-1.0.4.dist-info/entry_points.txt
tada_predict-1.0.4.dist-info/LICENSE
tada_predict-1.0.4.dist-info/WHEEL
tada_predict-1.0.4.dist-info/METADATA
tada_predict-1.0.4.dist-info/RECORD
