Metadata-Version: 2.1
Name: tada-predict
Version: 1.0.4
Summary: Predict the likely worst-case order-of-growth function for an arbitrary Python function.
Home-page: https://tada-predict.netlify.app
License: GPL-3.0
Author: Enpu You
Author-email: youe2@allegheny.edu
Maintainer: Enpu You
Maintainer-email: youe2@allegheny.edu
Requires-Python: >=3.6,<4.0
Classifier: License :: OSI Approved :: GNU General Public License v3 (GPLv3)
Classifier: Programming Language :: Python :: 3
Classifier: Programming Language :: Python :: 3.6
Classifier: Programming Language :: Python :: 3.7
Classifier: Programming Language :: Python :: 3.8
Classifier: Programming Language :: Python :: 3.9
Requires-Dist: colorama
Requires-Dist: hypothesis
Requires-Dist: hypothesis-jsonschema
Requires-Dist: markdown-include (>=0.6.0,<0.7.0)
Requires-Dist: matplotlib (>=3.3.0,<4.0.0)
Requires-Dist: mkdocs (>=1.1.2,<2.0.0)
Requires-Dist: mkdocs-git-revision-date-plugin (>=0.3.1,<0.4.0)
Requires-Dist: mkdocs-material (>=6.1.6,<7.0.0)
Requires-Dist: pandas
Requires-Dist: ptable
Requires-Dist: pyperf
Project-URL: Repository, https://github.com/Tada-Project/tada
